{"is_source_file": true, "format": "Dart", "description": "This file contains stub classes for CI environment to satisfy static analysis, providing minimal implementations of common provider classes used in Flutter state management.", "external_files": [], "external_methods": [], "published": ["ChangeNotifier", "ChangeNotifierProvider", "MultiProvider"], "classes": [{"name": "ChangeNotifier", "description": "A stub class representing ChangeNotifier, with an empty notifyListeners method."}, {"name": "ChangeNotifierProvider", "description": "A stub generic provider class with a required create function."}, {"name": "MultiProvider", "description": "A stub class representing a multi-provider widget, with required list of providers and a child."}], "methods": [{"name": "notifyListeners", "description": "Empty method to satisfy static analysis, does not perform any operation."}], "calls": [], "search-terms": ["provider", "CI-only", "stubs", "ChangeNotifier", "provider_ci_stubs", "static analyzer"], "state": 2, "file_id": 25, "knowledge_revision": 59, "git_revision": "", "hash": "421ebb91b47c54d17ec8369c957e094b", "format-version": 4, "code-base-name": "notes_frontend", "filename": "notes_frontend/lib/_ci_stubs/provider_stubs.dart", "revision_history": [{"59": ""}]}